quaeroml_serving/ModelH2o.py
quaeroml_serving/__init__.py
quaeroml_serving/pagekite.py
quaeroml_serving/server.py
quaeroml_serving/tests.py
quaeroml_serving/3rdparty/pagekite.py
quaeroml_serving-0.0.102.dist-info/DESCRIPTION.rst
quaeroml_serving-0.0.102.dist-info/METADATA
quaeroml_serving-0.0.102.dist-info/RECORD
quaeroml_serving-0.0.102.dist-info/WHEEL
quaeroml_serving-0.0.102.dist-info/entry_points.txt
quaeroml_serving-0.0.102.dist-info/metadata.json
quaeroml_serving-0.0.102.dist-info/top_level.txt
