Metadata-Version: 2.0
Name: quaeroml-serving
Version: 0.0.102
Summary: The easiest ML productionizer
Home-page: https://github.com/Quaero3/cdp/tree/models/quaeroml/quaeroml-serving
Author: David G Ortega
Author-email: david.ortega@quaero.com
License: UNKNOWN
Platform: UNKNOWN
Requires-Dist: flask
Requires-Dist: flask-monitoringdashboard
Requires-Dist: h2o (==3.18.0.8)
Requires-Dist: healthcheck
Requires-Dist: msgpack
Requires-Dist: numpy
Requires-Dist: pandas
Requires-Dist: py-eureka-client
Requires-Dist: pyyaml
